[
    {
        "nombre":"Samsung a04e",
        "gama":"media",
        "descripcion":"telefono samsung de buena calidad, de la familia A0 con buena calificacion",
        "modelo":"X203OS",
        "id": 1,
        "precio": 120000,
        "frabricante":"Samsung",
        "oferta": true,
        "calificacion": 4.3,
        "ram": "4gb",
        "bateria": "5000mAh",
        "almacenamiento": "128gb",
        "procesador": "snapdragon 480",
        "imagen":"samsung/samsung-galaxi-a04e-frente-negro.png",
        "ventas": 23
    },{
        "nombre":"Motorola g52",
        "gama":"baja",
        "descripcion":"telefono motorola de buena calidad, de la familia e con mala calificacion",
        "modelo":"T330I",
        "id": 2,
        "precio": 40000,
        "frabricante":"MOTOROLA",
        "oferta": false,
        "calificacion": 2.1,
        "ram": "2gb",
        "bateria": "4000mAh",
        "almacenamiento": "64gb",
        "procesador": "mediatek 280",
        "imagen":"motorola/g52-azul-frente.png",
        "ventas": 3
    },{
        "nombre":"Xiaomi redmi note11",
        "gama":"media",
        "descripcion":"telefono motorola de buena calidad, de la familia note con mala calificacion",
        "modelo":"T1740I",
        "id": 3,
        "precio": 240000,
        "frabricante":"XIAOMI",
        "oferta": false,
        "calificacion": 4.1,
        "ram": "6gb",
        "bateria": "5000mAh",
        "almacenamiento": "128gb",
        "procesador": "snapdragon 480",
        "imagen":"xiaomi/Xiaomi-redmi-note-11-frente-negro.png",
        "ventas": 10
    }
]